gamulet/__init__.py
gamulet/exceptions.py
gamulet/gamulet.py
gamulet/logger.py
gamulet/utils.py
gamulet/validations.py
gamulet-0.1.0.dist-info/METADATA
gamulet-0.1.0.dist-info/WHEEL
gamulet-0.1.0.dist-info/RECORD
